setup.py
alphadict/__init__.py
alphadict/alphadict.py
alphadict/test_alphadict.py
alphadict.egg-info/PKG-INFO
alphadict.egg-info/SOURCES.txt
alphadict.egg-info/dependency_links.txt
alphadict.egg-info/not-zip-safe
alphadict.egg-info/top_level.txt