Metadata-Version: 1.0
Name: alphadict
Version: 1.01
Summary: Recursively sorts dictionaries by key.
Home-page: https://github.com/dancrew32/AlphaDict
Author: Dan Masquelier
Author-email: dmasquelier@gmail.com
License: MIT
Platform: UNKNOWN
